lyra2re2_hash_test.cp38-win32.pyd
lyra2re3_hash_test.cp38-win32.pyd
lyra2re_hash_test.cp38-win32.pyd
verthash_test.cp38-win32.pyd
vtc_scrypt_new_test.cp38-win32.pyd
vertcoinhash_test-0.1.2.dist-info/LICENSE
vertcoinhash_test-0.1.2.dist-info/METADATA
vertcoinhash_test-0.1.2.dist-info/WHEEL
vertcoinhash_test-0.1.2.dist-info/top_level.txt
vertcoinhash_test-0.1.2.dist-info/RECORD
