Metadata-Version: 2.1
Name: vertcoinhash_test
Version: 0.1.2
Summary: Bindings for proof of work used by Vertcoin
Home-page: https://github.com/vertiond/vertcoinhash-python
Author: vertion
Author-email: vertion@protonmail.com
License: UNKNOWN
Platform: UNKNOWN
License-File: LICENSE
